tenzro_cortex-0.1.0.dist-info/licenses/LICENSE
tenzro_cortex_cli/__init__.py
tenzro_cortex_cli/cli.py
tenzro_cortex_cli/cli_fixed.py
tenzro_cortex-0.1.0.dist-info/METADATA
tenzro_cortex-0.1.0.dist-info/WHEEL
tenzro_cortex-0.1.0.dist-info/entry_points.txt
tenzro_cortex-0.1.0.dist-info/top_level.txt
tenzro_cortex-0.1.0.dist-info/RECORD
